atc/__init__.py
atc/alias.py
atc/db_auto.py
atc/functions.py
atc/spark.py
atc/transformations.py
atc/version.py
atc/cache/CachedLoader.py
atc/cache/CachedLoaderParameters.py
atc/cache/__init__.py
atc/config_master/__init__.py
atc/configurator/__init__.py
atc/configurator/configurator.py
atc/configurator/_cli/__init__.py
atc/configurator/_cli/generate_keys_file.py
atc/configurator/sql/StatementBlocks.py
atc/configurator/sql/__init__.py
atc/configurator/sql/comments.py
atc/configurator/sql/create.py
atc/configurator/sql/db.py
atc/configurator/sql/exceptions.py
atc/configurator/sql/init_sqlparse.py
atc/configurator/sql/parse_sql.py
atc/configurator/sql/substructures.py
atc/configurator/sql/table.py
atc/configurator/sql/types.py
atc/configurator/sql/utils.py
atc/configurator/sql/sqlparse/__init__.py
atc/configurator/sql/sqlparse/__main__.py
atc/configurator/sql/sqlparse/cli.py
atc/configurator/sql/sqlparse/exceptions.py
atc/configurator/sql/sqlparse/formatter.py
atc/configurator/sql/sqlparse/keywords.py
atc/configurator/sql/sqlparse/lexer.py
atc/configurator/sql/sqlparse/sql.py
atc/configurator/sql/sqlparse/tokens.py
atc/configurator/sql/sqlparse/utils.py
atc/configurator/sql/sqlparse/engine/__init__.py
atc/configurator/sql/sqlparse/engine/filter_stack.py
atc/configurator/sql/sqlparse/engine/grouping.py
atc/configurator/sql/sqlparse/engine/statement_splitter.py
atc/configurator/sql/sqlparse/filters/__init__.py
atc/configurator/sql/sqlparse/filters/aligned_indent.py
atc/configurator/sql/sqlparse/filters/others.py
atc/configurator/sql/sqlparse/filters/output.py
atc/configurator/sql/sqlparse/filters/reindent.py
atc/configurator/sql/sqlparse/filters/right_margin.py
atc/configurator/sql/sqlparse/filters/tokens.py
atc/cosmos/__init__.py
atc/cosmos/cosmos.py
atc/cosmos/cosmos_base_server.py
atc/cosmos/cosmos_handle.py
atc/delta/__init__.py
atc/delta/db_handle.py
atc/delta/delta_handle.py
atc/eh/EventHubCapture.py
atc/eh/EventHubCaptureExtractor.py
atc_dataplatform-1.1.69.dist-info/LICENSE
atc_dataplatform-1.1.69.dist-info/METADATA
atc_dataplatform-1.1.69.dist-info/WHEEL
atc_dataplatform-1.1.69.dist-info/entry_points.txt
atc_dataplatform-1.1.69.dist-info/top_level.txt
atc_dataplatform-1.1.69.dist-info/RECORD
