Metadata-Version: 2.1
Name: atc-dataplatform
Version: 1.1.69
Summary: A common set of python libraries for DataBricks
Home-page: https://github.com/atc-net/atc-dataplatform
Author: ATC.Net
Author-email: atcnet.org@gmail.com
License: UNKNOWN
Project-URL: Documentation, https://github.com/atc-net/atc-dataplatform
Project-URL: Bug Reports, https://github.com/atc-net/atc-dataplatform/issues
Project-URL: Source Code, https://github.com/atc-net/atc-dataplatform
Keywords: databricks,pyspark
Platform: UNKNOWN
Classifier: Development Status :: 2 - Pre-Alpha
Classifier: Intended Audience :: Developers
Classifier: Topic :: Software Development :: Build Tools
Classifier: Programming Language :: Python :: 3
Classifier: Programming Language :: Python :: 3.8
Classifier: Programming Language :: Python :: 3 :: Only
Classifier: License :: OSI Approved :: MIT License
Classifier: Operating System :: OS Independent
Requires-Python: >=3.8
Requires-Dist: pyyaml
Requires-Dist: sqlparse
Requires-Dist: Deprecated
Requires-Dist: pyodbc
Requires-Dist: databricks-api
Requires-Dist: importlib-metadata
Requires-Dist: azure-cosmos
Requires-Dist: timezonefinder (==6.0.2)
Requires-Dist: more-itertools
